runaway/__init__.py
runaway/actions.py
runaway/core.py
runaway/handlers.py
runaway/signals.py
runaway/testing.py
runaway/extras/__init__.py
runaway/extras/ainput.py
runaway/extras/looping.py
runaway-0.2.1.dist-info/DESCRIPTION.rst
runaway-0.2.1.dist-info/METADATA
runaway-0.2.1.dist-info/RECORD
runaway-0.2.1.dist-info/WHEEL
runaway-0.2.1.dist-info/metadata.json
runaway-0.2.1.dist-info/top_level.txt
