Metadata-Version: 2.0
Name: runaway
Version: 0.2.1
Summary: Coroutine runner
Home-page: https://gitlab.com/toejough/runaway
Author: toejough
Author-email: toejough@gmail.com
License: Apache 2.0
Keywords: coroutine generator executor execute test run
Platform: UNKNOWN
Classifier: Development Status :: 3 - Alpha
Classifier: Intended Audience :: Developers
Classifier: License :: OSI Approved :: Apache Software License
Classifier: Programming Language :: Python :: 3
Classifier: Programming Language :: Python :: 3.6
Requires-Dist: utaw
Provides-Extra: checkers
Requires-Dist: dodgy; extra == 'checkers'
Requires-Dist: flake8-bugbear; extra == 'checkers'
Requires-Dist: flake8-docstrings; extra == 'checkers'
Requires-Dist: flake8-import-order; extra == 'checkers'
Requires-Dist: mypy; extra == 'checkers'
Requires-Dist: otter; extra == 'checkers'
Requires-Dist: pocketwalk; extra == 'checkers'
Requires-Dist: pylint; extra == 'checkers'
Requires-Dist: vulture; extra == 'checkers'
